blackmarble/__init__.py
blackmarble/__main__.py
blackmarble/core.py
blackmarble/download.py
blackmarble/extract.py
blackmarble/raster.py
blackmarble/types.py
blackmarble/data/blackmarbletiles.geojson
blackmarblepy-2025.11.2.dist-info/METADATA
blackmarblepy-2025.11.2.dist-info/WHEEL
blackmarblepy-2025.11.2.dist-info/licenses/LICENSE
blackmarblepy-2025.11.2.dist-info/RECORD
