Metadata-Version: 2.4
Name: blackmarblepy
Version: 2025.11.2
Summary: Georeferenced Rasters of Nighttime Lights from NASA Black Marble data
Project-URL: Homepage, https://worldbank.github.io/blackmarblepy
Project-URL: Bug Reports, https://github.com/worldbank/blackmarblepy/issues
Project-URL: Source, https://github.com/worldbank/blackmarblepy
Author-email: Gabriel Stefanini Vicente <gvicente@worldbank.org>, Robert Marty <rmarty@worldbank.org>
Maintainer-email: Gabriel Stefanini Vicente <gvicente@worldbank.org>, World Bank <github@worldbank.org>
License: Mozilla Public License Version 2.0
License-File: LICENSE
Keywords: nasa black marble,nighttime lights,world bank
Classifier: Intended Audience :: Science/Research
Classifier: Natural Language :: English
Classifier: Operating System :: OS Independent
Classifier: Programming Language :: Python :: 3
Classifier: Programming Language :: Python :: 3 :: Only
Classifier: Programming Language :: Python :: 3.10
Classifier: Programming Language :: Python :: 3.11
Classifier: Programming Language :: Python :: 3.12
Classifier: Programming Language :: Python :: 3.13
Classifier: Topic :: Scientific/Engineering
Classifier: Topic :: Scientific/Engineering :: GIS
Requires-Python: >=3.10
Requires-Dist: aiohttp>=3.12.7
Requires-Dist: geopandas<2
Requires-Dist: h5py>=3.13.0
Requires-Dist: httpx>=0.28.1
Requires-Dist: humanize>=4.12.3
Requires-Dist: ipywidgets<9
Requires-Dist: nest-asyncio<2
Requires-Dist: numpy<3,>=1.21.0
Requires-Dist: pandas<3,>=2
Requires-Dist: pqdm>=0.2.0
Requires-Dist: pydantic<3,>2
Requires-Dist: rasterio<2,>=1
Requires-Dist: rasterstats>=0.20.0
Requires-Dist: rioxarray<0.18.0,>=0.15.1
Requires-Dist: tenacity>=9.1.2
Requires-Dist: tqdm>=4.67.1
Requires-Dist: xarray>=0.7.0
Provides-Extra: docs
Requires-Dist: docutils==0.17.1; extra == 'docs'
Requires-Dist: jupyter-book<2,>=0.15.1; extra == 'docs'
Requires-Dist: sphinxcontrib-apidoc<1,>=0.4.0; extra == 'docs'
Requires-Dist: standard-imghdr>=3.13.0; extra == 'docs'
Provides-Extra: examples
Requires-Dist: bokeh>=3.7.3; extra == 'examples'
Requires-Dist: colorcet>=3.1.0; extra == 'examples'
Requires-Dist: contextily>=1.6.2; extra == 'examples'
Requires-Dist: folium>=0.19.7; extra == 'examples'
Requires-Dist: mapclassify>=2.8.1; extra == 'examples'
Requires-Dist: python-dotenv>=1.1.0; extra == 'examples'
Requires-Dist: watermark>=2.5.0; extra == 'examples'
Provides-Extra: tests
Requires-Dist: pytest; extra == 'tests'
